{
	"info": {
		"_postman_id": "da233788-205a-45fb-8a9e-63ede327b280",
		"name": "ExpressJS",
		"schema": "https://schema.getpostman.com/json/collection/v2.1.0/collection.json"
	},
	"item": [
		{
			"name": "GET ALL",
			"protocolProfileBehavior": {
				"disableBodyPruning": true
			},
			"request": {
				"method": "GET",
				"header": [],
				"body": {
					"mode": "raw",
					"raw": "",
					"options": {
						"raw": {
							"language": "json"
						}
					}
				},
				"url": {
					"raw": "http://localhost:4000/user",
					"protocol": "http",
					"host": [
						"localhost"
					],
					"port": "4000",
					"path": [
						"user"
					]
				}
			},
			"response": []
		},
		{
			"name": "POST",
			"request": {
				"method": "POST",
				"header": [],
				"body": {
					"mode": "raw",
					"raw": "{ \"name\": \"sasha\", \"password\":\"123\", \"profession\": \"easy junior\", \"age\": 28 , \"email\":\"yarnc.com\"}",
					"options": {
						"raw": {
							"language": "json"
						}
					}
				},
				"url": {
					"raw": "http://localhost:4000/user",
					"protocol": "http",
					"host": [
						"localhost"
					],
					"port": "4000",
					"path": [
						"user"
					]
				}
			},
			"response": []
		},
		{
			"name": "PUT",
			"request": {
				"method": "PUT",
				"header": [],
				"body": {
					"mode": "raw",
					"raw": "{ \"name\":\"PUTUSER2\", \"profession\": \"UI/UX design\", \"age\": 29, \"email\":\"put@mail.ru\"}",
					"options": {
						"raw": {
							"language": "json"
						}
					}
				},
				"url": {
					"raw": "http://localhost:4000/user/16",
					"protocol": "http",
					"host": [
						"localhost"
					],
					"port": "4000",
					"path": [
						"user",
						"16"
					]
				}
			},
			"response": []
		},
		{
			"name": "DELETE",
			"request": {
				"method": "DELETE",
				"header": [],
				"url": {
					"raw": "http://localhost:4000/user/9",
					"protocol": "http",
					"host": [
						"localhost"
					],
					"port": "4000",
					"path": [
						"user",
						"9"
					]
				}
			},
			"response": []
		},
		{
			"name": "REFRESHUSER",
			"request": {
				"method": "GET",
				"header": [],
				"url": {
					"raw": "http://localhost:4000/user/12",
					"protocol": "http",
					"host": [
						"localhost"
					],
					"port": "4000",
					"path": [
						"user",
						"12"
					]
				}
			},
			"response": []
		},
		{
			"name": "Register",
			"request": {
				"method": "POST",
				"header": [],
				"body": {
					"mode": "raw",
					"raw": "{\r\n        \"name\": \"sasha\",\r\n        \"profession\": \"easy junior\",\r\n        \"age\": 28,\r\n        \"email\": \"yarn2c.com\",\r\n        \"password\": \"123\"\r\n}",
					"options": {
						"raw": {
							"language": "json"
						}
					}
				},
				"url": {
					"raw": "http://localhost:4000/register",
					"protocol": "http",
					"host": [
						"localhost"
					],
					"port": "4000",
					"path": [
						"register"
					]
				}
			},
			"response": []
		},
		{
			"name": "login",
			"request": {
				"method": "GET",
				"header": []
			},
			"response": []
		},
		{
			"name": "info",
			"request": {
				"method": "GET",
				"header": [
					{
						"key": "Authorization",
						"value": "Bearer eyJhbGciOiJIUzI1NiIsInR5cCI6IkpXVCJ9.eyJlbWFpbCI6Inlhcm4xQGMuY29tIiwiaWF0IjoxNjUwMDYzMTEzLCJleHAiOjE2NTAxNDk1MTN9.zvE7-7vUU9b7A7UhlQMhVWFrEZ2uYl9ybhHC8inacX4",
						"type": "text"
					}
				],
				"url": {
					"raw": "http://localhost:4000/info",
					"protocol": "http",
					"host": [
						"localhost"
					],
					"port": "4000",
					"path": [
						"info"
					]
				}
			},
			"response": []
		},
		{
			"name": "upload",
			"request": {
				"method": "GET",
				"header": []
			},
			"response": []
		}
	]
}